coach/__init__.py
coach/coach.py
coach_ml-0.22.dist-info/LICENSE
coach_ml-0.22.dist-info/METADATA
coach_ml-0.22.dist-info/WHEEL
coach_ml-0.22.dist-info/top_level.txt
coach_ml-0.22.dist-info/RECORD
