Metadata-Version: 2.1
Name: coach-ml
Version: 0.22
Summary: Python client for coach
Home-page: https://github.com/coach-ml/coach-python
Author: Loren Kuich
Author-email: loren@lkuich.com
License: UNKNOWN
Platform: UNKNOWN
Classifier: Programming Language :: Python :: 3.6
Classifier: Programming Language :: Python :: 3.7
Classifier: License :: OSI Approved :: MIT License
Classifier: Operating System :: OS Independent
Requires-Dist: requests
Requires-Dist: numpy (==1.16.4)
Requires-Dist: tensorflow (==1.14)
Requires-Dist: imageio (==2.6.1)
